{
    "_index": "atlan-query-logs",
    "_type": "logs",
    "_id": "20191210_092032_00000_e5hkw",
    "_version": 2,
    "_score": null,
    "_source": {
        "schema": "default",
        "createdAt": "2019-12-10T09:20:32.889Z",
        "catalog": "hive",
        "query": "select count(*) from data_table",
        "clientIp": "192.168.16.17",
        "serverAddress": "192.168.43.178",
        "loggerVersion": "v1.1",
        "userAgent": "StatementClientV1/326",
        "state": "FINISHED",
        "source": "presto-cli",
        "user": "arpit.s",
        "queryType": [
            "SELECT",
            "COUNT"
        ],
        "physicalInputRows": 3072000000,
        "analysisTime": 1,
        "serverVersion": "312-e.4",
        "queryPayload": "{\"stageId\":\"20191210_092032_00000_e5hkw.0\",\"state\":\"FINISHED\",\"self\":\"http://192.168.43.178:8080/v1/stage/20191210_092032_00000_e5hkw.0\",\"plan\":{\"id\":\"0\",\"root\":{\"@type\":\"output\",\"id\":\"14\",\"source\":{\"@type\":\"aggregation\",\"id\":\"9\",\"source\":{\"@type\":\"exchange\",\"id\":\"170\",\"type\":\"GATHER\",\"scope\":\"LOCAL\",\"partitioningScheme\":{\"partitioning\":{\"handle\":{\"connectorHandle\":{\"@type\":\"$remote\",\"partitioning\":\"SINGLE\",\"function\":\"SINGLE\"}},\"arguments\":[]},\"outputLayout\":[\"count_88\"],\"replicateNullsAndAny\":false},\"sources\":[{\"@type\":\"remoteSource\",\"id\":\"176\",\"sourceFragmentIds\":[\"1\"],\"outputs\":[\"count_88\"],\"exchangeType\":\"GATHER\"}],\"inputs\":[[\"count_88\"]]},\"aggregations\":{\"count\":{\"call\":\"\\\"count\\\"(\\\"count_88\\\")\",\"signature\":{\"name\":\"count\",\"kind\":\"AGGREGATE\",\"typeVariableConstraints\":[],\"longVariableConstraints\":[],\"returnType\":\"bigint\",\"argumentTypes\":[],\"variableArity\":false}}},\"groupingSets\":{\"groupingKeys\":[],\"groupingSetCount\":1,\"globalGroupingSets\":[0]},\"preGroupedSymbols\":[],\"step\":\"FINAL\"},\"columns\":[\"_col0\"],\"outputs\":[\"count\"]},\"symbols\":{\"count\":\"bigint\",\"count_88\":\"bigint\"},\"partitioning\":{\"connectorHandle\":{\"@type\":\"$remote\",\"partitioning\":\"SINGLE\",\"function\":\"SINGLE\"}},\"partitionedSources\":[],\"partitioningScheme\":{\"partitioning\":{\"handle\":{\"connectorHandle\":{\"@type\":\"$remote\",\"partitioning\":\"SINGLE\",\"function\":\"SINGLE\"}},\"arguments\":[]},\"outputLayout\":[\"count\"],\"replicateNullsAndAny\":false,\"bucketToPartition\":[0]},\"stageExecutionDescriptor\":{\"strategy\":\"UNGROUPED_EXECUTION\",\"groupedExecutionScanNodes\":[]},\"statsAndCosts\":{\"stats\":{\"14\":{\"outputRowCount\":\"NaN\",\"symbolStatistics\":{}},\"9\":{\"outputRowCount\":\"NaN\",\"symbolStatistics\":{}},\"170\":{\"outputRowCount\":\"NaN\",\"symbolStatistics\":{}},\"176\":{\"outputRowCount\":\"NaN\",\"symbolStatistics\":{}}},\"costs\":{\"14\":{\"cpuCost\":\"NaN\",\"maxMemory\":\"NaN\",\"maxMemoryWhenOutputting\":\"NaN\",\"networkCost\":\"NaN\",\"rootNodeLocalCostEstimate\":{\"cpuCost\":0.0,\"maxMemory\":0.0,\"networkCost\":0.0}},\"9\":{\"cpuCost\":\"NaN\",\"maxMemory\":\"NaN\",\"maxMemoryWhenOutputting\":\"NaN\",\"networkCost\":\"NaN\",\"rootNodeLocalCostEstimate\":{\"cpuCost\":\"NaN\",\"maxMemory\":\"NaN\",\"networkCost\":0.0}},\"170\":{\"cpuCost\":\"NaN\",\"maxMemory\":\"NaN\",\"maxMemoryWhenOutputting\":\"NaN\",\"networkCost\":\"NaN\",\"rootNodeLocalCostEstimate\":{\"cpuCost\":0.0,\"maxMemory\":0.0,\"networkCost\":0.0}},\"176\":{\"cpuCost\":\"NaN\",\"maxMemory\":\"NaN\",\"maxMemoryWhenOutputting\":\"NaN\",\"networkCost\":\"NaN\",\"rootNodeLocalCostEstimate\":{\"cpuCost\":0.0,\"maxMemory\":0.0,\"networkCost\":\"NaN\"}}}},\"jsonRepresentation\":\"{\\n  \\\"id\\\" : \\\"14\\\",\\n  \\\"name\\\" : \\\"Output\\\",\\n  \\\"identifier\\\" : \\\"[_col0]\\\",\\n  \\\"details\\\" : \\\"_col0 := count\\\\n\\\",\\n  \\\"children\\\" : [ {\\n    \\\"id\\\" : \\\"9\\\",\\n    \\\"name\\\" : \\\"Aggregate(FINAL)\\\",\\n    \\\"identifier\\\" : \\\"\\\",\\n    \\\"details\\\" : \\\"count := \\\\\\\"count\\\\\\\"(\\\\\\\"count_88\\\\\\\")\\\\n\\\",\\n    \\\"children\\\" : [ {\\n      \\\"id\\\" : \\\"170\\\",\\n      \\\"name\\\" : \\\"LocalExchange\\\",\\n      \\\"identifier\\\" : \\\"[SINGLE] ()\\\",\\n      \\\"details\\\" : \\\"\\\",\\n      \\\"children\\\" : [ {\\n        \\\"id\\\" : \\\"176\\\",\\n        \\\"name\\\" : \\\"RemoteSource\\\",\\n        \\\"identifier\\\" : \\\"[1]\\\",\\n        \\\"details\\\" : \\\"\\\",\\n        \\\"children\\\" : [ ],\\n        \\\"remoteSources\\\" : [ \\\"1\\\" ]\\n      } ],\\n      \\\"remoteSources\\\" : [ ]\\n    } ],\\n    \\\"remoteSources\\\" : [ ]\\n  } ],\\n  \\\"remoteSources\\\" : [ ]\\n}\"},\"types\":[\"bigint\"],\"stageStats\":{\"schedulingComplete\":\"2019-12-10T09:20:35.958Z\",\"getSplitDistribution\":{\"maxError\":\"NaN\",\"count\":0.0,\"total\":0.0,\"p01\":-9223372036854775808,\"p05\":-9223372036854775808,\"p10\":-9223372036854775808,\"p25\":-9223372036854775808,\"p50\":-9223372036854775808,\"p75\":-9223372036854775808,\"p90\":-9223372036854775808,\"p95\":-9223372036854775808,\"p99\":-9223372036854775808,\"min\":9223372036854775807,\"max\":-9223372036854775808,\"avg\":\"NaN\"},\"totalTasks\":1,\"runningTasks\":0,\"completedTasks\":1,\"totalDrivers\":17,\"queuedDrivers\":0,\"runningDrivers\":0,\"blockedDrivers\":0,\"completedDrivers\":17,\"cumulativeUserMemory\":583059.0,\"userMemoryReservation\":\"0B\",\"revocableMemoryReservation\":\"0B\",\"totalMemoryReservation\":\"0B\",\"peakUserMemoryReservation\":\"24B\",\"peakRevocableMemoryReservation\":\"0B\",\"totalScheduledTime\":\"287.61ms\",\"totalCpuTime\":\"136.86ms\",\"totalBlockedTime\":\"3.52m\",\"fullyBlocked\":false,\"blockedReasons\":[],\"physicalInputDataSize\":\"0B\",\"physicalInputPositions\":0,\"internalNetworkInputDataSize\":\"33.21kB\",\"internalNetworkInputPositions\":1097,\"rawInputDataSize\":\"33.21kB\",\"rawInputPositions\":1097,\"processedInputDataSize\":\"9.64kB\",\"processedInputPositions\":1097,\"bufferedDataSize\":\"0B\",\"outputDataSize\":\"9B\",\"outputPositions\":1,\"physicalWrittenDataSize\":\"0B\",\"gcInfo\":{\"stageId\":0,\"tasks\":1,\"fullGcTasks\":0,\"minFullGcSec\":0,\"maxFullGcSec\":0,\"totalFullGcSec\":0,\"averageFullGcSec\":0},\"operatorSummaries\":[{\"stageId\":0,\"pipelineId\":0,\"operatorId\":0,\"planNodeId\":\"176\",\"operatorType\":\"ExchangeOperator\",\"totalDrivers\":16,\"addInputCalls\":0,\"addInputWall\":\"0.00ns\",\"addInputCpu\":\"0.00ns\",\"physicalInputDataSize\":\"0B\",\"physicalInputPositions\":0,\"internalNetworkInputDataSize\":\"33.21kB\",\"internalNetworkInputPositions\":1097,\"rawInputDataSize\":\"33.21kB\",\"inputDataSize\":\"9.64kB\",\"inputPositions\":1097,\"sumSquaredInputPositions\":800179.0,\"getOutputCalls\":1110,\"getOutputWall\":\"82.09ms\",\"getOutputCpu\":\"34.66ms\",\"outputDataSize\":\"9.64kB\",\"outputPositions\":1097,\"physicalWrittenDataSize\":\"0B\",\"blockedWall\":\"3.15m\",\"finishCalls\":0,\"finishWall\":\"0.00ns\",\"finishCpu\":\"0.00ns\",\"userMemoryReservation\":\"0B\",\"revocableMemoryReservation\":\"0B\",\"systemMemoryReservation\":\"0B\",\"peakUserMemoryReservation\":\"0B\",\"peakSystemMemoryReservation\":\"0B\",\"peakRevocableMemoryReservation\":\"0B\",\"peakTotalMemoryReservation\":\"0B\",\"spilledDataSize\":\"0B\",\"info\":{\"@type\":\"exchangeClientStatus\",\"bufferedBytes\":0,\"maxBufferedBytes\":889,\"averageBytesPerRequest\":0,\"successfulRequestsCount\":17520,\"bufferedPages\":0,\"noMoreLocations\":true,\"pageBufferClientStatuses\":[]}},{\"stageId\":0,\"pipelineId\":1,\"operatorId\":0,\"planNodeId\":\"170\",\"operatorType\":\"LocalExchangeSourceOperator\",\"totalDrivers\":1,\"addInputCalls\":0,\"addInputWall\":\"0.00ns\",\"addInputCpu\":\"0.00ns\",\"physicalInputDataSize\":\"0B\",\"physicalInputPositions\":0,\"internalNetworkInputDataSize\":\"0B\",\"internalNetworkInputPositions\":0,\"rawInputDataSize\":\"0B\",\"inputDataSize\":\"9.64kB\",\"inputPositions\":1097,\"sumSquaredInputPositions\":1203409.0,\"getOutputCalls\":1097,\"getOutputWall\":\"12.31ms\",\"getOutputCpu\":\"9.61ms\",\"outputDataSize\":\"9.64kB\",\"outputPositions\":1097,\"physicalWrittenDataSize\":\"0B\",\"blockedWall\":\"22.14s\",\"finishCalls\":0,\"finishWall\":\"0.00ns\",\"finishCpu\":\"0.00ns\",\"userMemoryReservation\":\"0B\",\"revocableMemoryReservation\":\"0B\",\"systemMemoryReservation\":\"0B\",\"peakUserMemoryReservation\":\"0B\",\"peakSystemMemoryReservation\":\"0B\",\"peakRevocableMemoryReservation\":\"0B\",\"peakTotalMemoryReservation\":\"0B\",\"spilledDataSize\":\"0B\"},{\"stageId\":0,\"pipelineId\":0,\"operatorId\":1,\"planNodeId\":\"170\",\"operatorType\":\"LocalExchangeSinkOperator\",\"totalDrivers\":16,\"addInputCalls\":1097,\"addInputWall\":\"85.19ms\",\"addInputCpu\":\"21.16ms\",\"physicalInputDataSize\":\"0B\",\"physicalInputPositions\":0,\"internalNetworkInputDataSize\":\"0B\",\"internalNetworkInputPositions\":0,\"rawInputDataSize\":\"0B\",\"inputDataSize\":\"9.64kB\",\"inputPositions\":1097,\"sumSquaredInputPositions\":800179.0,\"getOutputCalls\":0,\"getOutputWall\":\"0.00ns\",\"getOutputCpu\":\"0.00ns\",\"outputDataSize\":\"9.64kB\",\"outputPositions\":1097,\"physicalWrittenDataSize\":\"0B\",\"blockedWall\":\"0.00ns\",\"finishCalls\":16,\"finishWall\":\"2.29ms\",\"finishCpu\":\"806.26us\",\"userMemoryReservation\":\"0B\",\"revocableMemoryReservation\":\"0B\",\"systemMemoryReservation\":\"0B\",\"peakUserMemoryReservation\":\"0B\",\"peakSystemMemoryReservation\":\"0B\",\"peakRevocableMemoryReservation\":\"0B\",\"peakTotalMemoryReservation\":\"0B\",\"spilledDataSize\":\"0B\"},{\"stageId\":0,\"pipelineId\":1,\"operatorId\":1,\"planNodeId\":\"9\",\"operatorType\":\"AggregationOperator\",\"totalDrivers\":1,\"addInputCalls\":1097,\"addInputWall\":\"10.09ms\",\"addInputCpu\":\"8.64ms\",\"physicalInputDataSize\":\"0B\",\"physicalInputPositions\":0,\"internalNetworkInputDataSize\":\"0B\",\"internalNetworkInputPositions\":0,\"rawInputDataSize\":\"0B\",\"inputDataSize\":\"9.64kB\",\"inputPositions\":1097,\"sumSquaredInputPositions\":1203409.0,\"getOutputCalls\":1580,\"getOutputWall\":\"7.67ms\",\"getOutputCpu\":\"4.75ms\",\"outputDataSize\":\"9B\",\"outputPositions\":1,\"physicalWrittenDataSize\":\"0B\",\"blockedWall\":\"0.00ns\",\"finishCalls\":1,\"finishWall\":\"23.81us\",\"finishCpu\":\"22.44us\",\"userMemoryReservation\":\"0B\",\"revocableMemoryReservation\":\"0B\",\"systemMemoryReservation\":\"0B\",\"peakUserMemoryReservation\":\"24B\",\"peakSystemMemoryReservation\":\"0B\",\"peakRevocableMemoryReservation\":\"0B\",\"peakTotalMemoryReservation\":\"24B\",\"spilledDataSize\":\"0B\"},{\"stageId\":0,\"pipelineId\":1,\"operatorId\":2,\"planNodeId\":\"14\",\"operatorType\":\"TaskOutputOperator\",\"totalDrivers\":1,\"addInputCalls\":1,\"addInputWall\":\"98.74us\",\"addInputCpu\":\"99.31us\",\"physicalInputDataSize\":\"0B\",\"physicalInputPositions\":0,\"internalNetworkInputDataSize\":\"0B\",\"internalNetworkInputPositions\":0,\"rawInputDataSize\":\"0B\",\"inputDataSize\":\"9B\",\"inputPositions\":1,\"sumSquaredInputPositions\":1.0,\"getOutputCalls\":0,\"getOutputWall\":\"0.00ns\",\"getOutputCpu\":\"0.00ns\",\"outputDataSize\":\"9B\",\"outputPositions\":1,\"physicalWrittenDataSize\":\"0B\",\"blockedWall\":\"0.00ns\",\"finishCalls\":1,\"finishWall\":\"3.31us\",\"finishCpu\":\"3.34us\",\"userMemoryReservation\":\"0B\",\"revocableMemoryReservation\":\"0B\",\"systemMemoryReservation\":\"0B\",\"peakUserMemoryReservation\":\"0B\",\"peakSystemMemoryReservation\":\"0B\",\"peakRevocableMemoryReservation\":\"0B\",\"peakTotalMemoryReservation\":\"0B\",\"spilledDataSize\":\"0B\"}]},\"tasks\":[{\"taskStatus\":{\"taskId\":\"20191210_092032_00000_e5hkw.0.0\",\"taskInstanceId\":\"35198015-cd77-46aa-80b5-916da59e4fa6\",\"version\":332,\"state\":\"FINISHED\",\"self\":\"http://192.168.40.119:8080/v1/task/20191210_092032_00000_e5hkw.0.0\",\"nodeId\":\"i-0edd90e78624ec992\",\"completedDriverGroups\":[],\"failures\":[],\"queuedPartitionedDrivers\":0,\"runningPartitionedDrivers\":0,\"outputBufferOverutilized\":false,\"physicalWrittenDataSize\":\"0B\",\"memoryReservation\":\"0B\",\"systemMemoryReservation\":\"0B\",\"revocableMemoryReservation\":\"0B\",\"fullGcCount\":0,\"fullGcTime\":\"0.00ns\"},\"lastHeartbeat\":\"2019-12-10T09:21:01.867Z\",\"outputBuffers\":{\"type\":\"PARTITIONED\",\"state\":\"FINISHED\",\"canAddBuffers\":false,\"canAddPages\":false,\"totalBufferedBytes\":0,\"totalBufferedPages\":0,\"totalRowsSent\":1,\"totalPagesSent\":1,\"buffers\":[]},\"noMoreSplits\":[\"176\"],\"stats\":{\"createTime\":\"2019-12-10T09:20:35.939Z\",\"firstStartTime\":\"2019-12-10T09:20:36.197Z\",\"lastStartTime\":\"2019-12-10T09:20:36.203Z\",\"lastEndTime\":\"2019-12-10T09:21:01.842Z\",\"endTime\":\"2019-12-10T09:21:01.873Z\",\"elapsedTime\":\"25.69s\",\"queuedTime\":\"18.68ms\",\"totalDrivers\":17,\"queuedDrivers\":0,\"queuedPartitionedDrivers\":0,\"runningDrivers\":0,\"runningPartitionedDrivers\":0,\"blockedDrivers\":0,\"completedDrivers\":17,\"cumulativeUserMemory\":583059.2620319999,\"userMemoryReservation\":\"0B\",\"revocableMemoryReservation\":\"0B\",\"systemMemoryReservation\":\"0B\",\"totalScheduledTime\":\"287.61ms\",\"totalCpuTime\":\"136.86ms\",\"totalBlockedTime\":\"3.52m\",\"fullyBlocked\":false,\"blockedReasons\":[],\"physicalInputDataSize\":\"0B\",\"physicalInputPositions\":0,\"internalNetworkInputDataSize\":\"33.21kB\",\"internalNetworkInputPositions\":1097,\"rawInputDataSize\":\"33.21kB\",\"rawInputPositions\":1097,\"processedInputDataSize\":\"9.64kB\",\"processedInputPositions\":1097,\"outputDataSize\":\"9B\",\"outputPositions\":1,\"physicalWrittenDataSize\":\"0B\",\"fullGcCount\":0,\"fullGcTime\":\"0.00ns\",\"pipelines\":[{\"pipelineId\":0,\"firstStartTime\":\"2019-12-10T09:20:36.197Z\",\"lastStartTime\":\"2019-12-10T09:20:36.203Z\",\"lastEndTime\":\"2019-12-10T09:21:01.842Z\",\"inputPipeline\":true,\"outputPipeline\":false,\"totalDrivers\":16,\"queuedDrivers\":0,\"queuedPartitionedDrivers\":0,\"runningDrivers\":0,\"runningPartitionedDrivers\":0,\"blockedDrivers\":0,\"completedDrivers\":16,\"userMemoryReservation\":\"0B\",\"revocableMemoryReservation\":\"0B\",\"systemMemoryReservation\":\"0B\",\"queuedTime\":{\"maxError\":0.0,\"count\":16.0,\"total\":2.07979313E8,\"p01\":10673126,\"p05\":10673126,\"p10\":11266130,\"p25\":12325702,\"p50\":12902632,\"p75\":13466568,\"p90\":14807811,\"p95\":17267868,\"p99\":17267868,\"min\":10673126,\"max\":17267868,\"avg\":1.29987070625E7},\"elapsedTime\":{\"maxError\":0.0,\"count\":16.0,\"total\":4.10437352806E11,\"p01\":25649835701,\"p05\":25649835701,\"p10\":25650135351,\"p25\":25650758106,\"p50\":25652985724,\"p75\":25653585780,\"p90\":25653866246,\"p95\":25655962477,\"p99\":25655962477,\"min\":25649835701,\"max\":25655962477,\"avg\":2.5652334550375E10},\"totalScheduledTime\":\"252.82ms\",\"totalCpuTime\":\"110.16ms\",\"totalBlockedTime\":\"3.15m\",\"fullyBlocked\":false,\"blockedReasons\":[],\"physicalInputDataSize\":\"0B\",\"physicalInputPositions\":0,\"internalNetworkInputDataSize\":\"33.21kB\",\"internalNetworkInputPositions\":1097,\"rawInputDataSize\":\"33.21kB\",\"rawInputPositions\":1097,\"processedInputDataSize\":\"9.64kB\",\"processedInputPositions\":1097,\"outputDataSize\":\"9.64kB\",\"outputPositions\":1097,\"physicalWrittenDataSize\":\"0B\",\"operatorSummaries\":[{\"stageId\":0,\"pipelineId\":0,\"operatorId\":0,\"planNodeId\":\"176\",\"operatorType\":\"ExchangeOperator\",\"totalDrivers\":16,\"addInputCalls\":0,\"addInputWall\":\"0.00ns\",\"addInputCpu\":\"0.00ns\",\"physicalInputDataSize\":\"0B\",\"physicalInputPositions\":0,\"internalNetworkInputDataSize\":\"33.21kB\",\"internalNetworkInputPositions\":1097,\"rawInputDataSize\":\"33.21kB\",\"inputDataSize\":\"9.64kB\",\"inputPositions\":1097,\"sumSquaredInputPositions\":800179.0,\"getOutputCalls\":1110,\"getOutputWall\":\"82.09ms\",\"getOutputCpu\":\"34.66ms\",\"outputDataSize\":\"9.64kB\",\"outputPositions\":1097,\"physicalWrittenDataSize\":\"0B\",\"blockedWall\":\"3.15m\",\"finishCalls\":0,\"finishWall\":\"0.00ns\",\"finishCpu\":\"0.00ns\",\"userMemoryReservation\":\"0B\",\"revocableMemoryReservation\":\"0B\",\"systemMemoryReservation\":\"0B\",\"peakUserMemoryReservation\":\"0B\",\"peakSystemMemoryReservation\":\"0B\",\"peakRevocableMemoryReservation\":\"0B\",\"peakTotalMemoryReservation\":\"0B\",\"spilledDataSize\":\"0B\",\"info\":{\"@type\":\"exchangeClientStatus\",\"bufferedBytes\":0,\"maxBufferedBytes\":889,\"averageBytesPerRequest\":0,\"successfulRequestsCount\":17520,\"bufferedPages\":0,\"noMoreLocations\":true,\"pageBufferClientStatuses\":[]}},{\"stageId\":0,\"pipelineId\":0,\"operatorId\":1,\"planNodeId\":\"170\",\"operatorType\":\"LocalExchangeSinkOperator\",\"totalDrivers\":16,\"addInputCalls\":1097,\"addInputWall\":\"85.19ms\",\"addInputCpu\":\"21.16ms\",\"physicalInputDataSize\":\"0B\",\"physicalInputPositions\":0,\"internalNetworkInputDataSize\":\"0B\",\"internalNetworkInputPositions\":0,\"rawInputDataSize\":\"0B\",\"inputDataSize\":\"9.64kB\",\"inputPositions\":1097,\"sumSquaredInputPositions\":800179.0,\"getOutputCalls\":0,\"getOutputWall\":\"0.00ns\",\"getOutputCpu\":\"0.00ns\",\"outputDataSize\":\"9.64kB\",\"outputPositions\":1097,\"physicalWrittenDataSize\":\"0B\",\"blockedWall\":\"0.00ns\",\"finishCalls\":16,\"finishWall\":\"2.29ms\",\"finishCpu\":\"806.26us\",\"userMemoryReservation\":\"0B\",\"revocableMemoryReservation\":\"0B\",\"systemMemoryReservation\":\"0B\",\"peakUserMemoryReservation\":\"0B\",\"peakSystemMemoryReservation\":\"0B\",\"peakRevocableMemoryReservation\":\"0B\",\"peakTotalMemoryReservation\":\"0B\",\"spilledDataSize\":\"0B\"}],\"drivers\":[]},{\"pipelineId\":1,\"firstStartTime\":\"2019-12-10T09:20:36.203Z\",\"lastStartTime\":\"2019-12-10T09:20:36.203Z\",\"lastEndTime\":\"2019-12-10T09:21:01.842Z\",\"inputPipeline\":false,\"outputPipeline\":true,\"totalDrivers\":1,\"queuedDrivers\":0,\"queuedPartitionedDrivers\":0,\"runningDrivers\":0,\"runningPartitionedDrivers\":0,\"blockedDrivers\":0,\"completedDrivers\":1,\"userMemoryReservation\":\"0B\",\"revocableMemoryReservation\":\"0B\",\"systemMemoryReservation\":\"0B\",\"queuedTime\":{\"maxError\":0.0,\"count\":1.0,\"total\":1.6962943E7,\"p01\":16962943,\"p05\":16962943,\"p10\":16962943,\"p25\":16962943,\"p50\":16962943,\"p75\":16962943,\"p90\":16962943,\"p95\":16962943,\"p99\":16962943,\"min\":16962943,\"max\":16962943,\"avg\":1.6962943E7},\"elapsedTime\":{\"maxError\":0.0,\"count\":1.0,\"total\":2.5655768442E10,\"p01\":25655768442,\"p05\":25655768442,\"p10\":25655768442,\"p25\":25655768442,\"p50\":25655768442,\"p75\":25655768442,\"p90\":25655768442,\"p95\":25655768442,\"p99\":25655768442,\"min\":25655768442,\"max\":25655768442,\"avg\":2.5655768442E10},\"totalScheduledTime\":\"34.79ms\",\"totalCpuTime\":\"26.70ms\",\"totalBlockedTime\":\"22.14s\",\"fullyBlocked\":false,\"blockedReasons\":[],\"physicalInputDataSize\":\"0B\",\"physicalInputPositions\":0,\"internalNetworkInputDataSize\":\"0B\",\"internalNetworkInputPositions\":0,\"rawInputDataSize\":\"0B\",\"rawInputPositions\":1097,\"processedInputDataSize\":\"9.64kB\",\"processedInputPositions\":1097,\"outputDataSize\":\"9B\",\"outputPositions\":1,\"physicalWrittenDataSize\":\"0B\",\"operatorSummaries\":[{\"stageId\":0,\"pipelineId\":1,\"operatorId\":0,\"planNodeId\":\"170\",\"operatorType\":\"LocalExchangeSourceOperator\",\"totalDrivers\":1,\"addInputCalls\":0,\"addInputWall\":\"0.00ns\",\"addInputCpu\":\"0.00ns\",\"physicalInputDataSize\":\"0B\",\"physicalInputPositions\":0,\"internalNetworkInputDataSize\":\"0B\",\"internalNetworkInputPositions\":0,\"rawInputDataSize\":\"0B\",\"inputDataSize\":\"9.64kB\",\"inputPositions\":1097,\"sumSquaredInputPositions\":1203409.0,\"getOutputCalls\":1097,\"getOutputWall\":\"12.31ms\",\"getOutputCpu\":\"9.61ms\",\"outputDataSize\":\"9.64kB\",\"outputPositions\":1097,\"physicalWrittenDataSize\":\"0B\",\"blockedWall\":\"22.14s\",\"finishCalls\":0,\"finishWall\":\"0.00ns\",\"finishCpu\":\"0.00ns\",\"userMemoryReservation\":\"0B\",\"revocableMemoryReservation\":\"0B\",\"systemMemoryReservation\":\"0B\",\"peakUserMemoryReservation\":\"0B\",\"peakSystemMemoryReservation\":\"0B\",\"peakRevocableMemoryReservation\":\"0B\",\"peakTotalMemoryReservation\":\"0B\",\"spilledDataSize\":\"0B\"},{\"stageId\":0,\"pipelineId\":1,\"operatorId\":1,\"planNodeId\":\"9\",\"operatorType\":\"AggregationOperator\",\"totalDrivers\":1,\"addInputCalls\":1097,\"addInputWall\":\"10.09ms\",\"addInputCpu\":\"8.64ms\",\"physicalInputDataSize\":\"0B\",\"physicalInputPositions\":0,\"internalNetworkInputDataSize\":\"0B\",\"internalNetworkInputPositions\":0,\"rawInputDataSize\":\"0B\",\"inputDataSize\":\"9.64kB\",\"inputPositions\":1097,\"sumSquaredInputPositions\":1203409.0,\"getOutputCalls\":1580,\"getOutputWall\":\"7.67ms\",\"getOutputCpu\":\"4.75ms\",\"outputDataSize\":\"9B\",\"outputPositions\":1,\"physicalWrittenDataSize\":\"0B\",\"blockedWall\":\"0.00ns\",\"finishCalls\":1,\"finishWall\":\"23.81us\",\"finishCpu\":\"22.44us\",\"userMemoryReservation\":\"0B\",\"revocableMemoryReservation\":\"0B\",\"systemMemoryReservation\":\"0B\",\"peakUserMemoryReservation\":\"24B\",\"peakSystemMemoryReservation\":\"0B\",\"peakRevocableMemoryReservation\":\"0B\",\"peakTotalMemoryReservation\":\"24B\",\"spilledDataSize\":\"0B\"},{\"stageId\":0,\"pipelineId\":1,\"operatorId\":2,\"planNodeId\":\"14\",\"operatorType\":\"TaskOutputOperator\",\"totalDrivers\":1,\"addInputCalls\":1,\"addInputWall\":\"98.74us\",\"addInputCpu\":\"99.31us\",\"physicalInputDataSize\":\"0B\",\"physicalInputPositions\":0,\"internalNetworkInputDataSize\":\"0B\",\"internalNetworkInputPositions\":0,\"rawInputDataSize\":\"0B\",\"inputDataSize\":\"9B\",\"inputPositions\":1,\"sumSquaredInputPositions\":1.0,\"getOutputCalls\":0,\"getOutputWall\":\"0.00ns\",\"getOutputCpu\":\"0.00ns\",\"outputDataSize\":\"9B\",\"outputPositions\":1,\"physicalWrittenDataSize\":\"0B\",\"blockedWall\":\"0.00ns\",\"finishCalls\":1,\"finishWall\":\"3.31us\",\"finishCpu\":\"3.34us\",\"userMemoryReservation\":\"0B\",\"revocableMemoryReservation\":\"0B\",\"systemMemoryReservation\":\"0B\",\"peakUserMemoryReservation\":\"0B\",\"peakSystemMemoryReservation\":\"0B\",\"peakRevocableMemoryReservation\":\"0B\",\"peakTotalMemoryReservation\":\"0B\",\"spilledDataSize\":\"0B\"}],\"drivers\":[]}]},\"needsPlan\":false}],\"subStages\":[{\"stageId\":\"20191210_092032_00000_e5hkw.1\",\"state\":\"FINISHED\",\"self\":\"http://192.168.43.178:8080/v1/stage/20191210_092032_00000_e5hkw.1\",\"plan\":{\"id\":\"1\",\"root\":{\"@type\":\"aggregation\",\"id\":\"174\",\"source\":{\"@type\":\"tablescan\",\"id\":\"0\",\"table\":{\"catalogName\":\"hive\",\"connectorHandle\":{\"@type\":\"hive-hadoop2\",\"schemaName\":\"default\",\"tableName\":\"5de4aa6bf1138e000101f5fa_green\"},\"transaction\":{\"@type\":\"hive-hadoop2\",\"uuid\":\"b1da040c-629e-4d04-9c46-a3f6a8239fae\"},\"layout\":{\"@type\":\"hive-hadoop2\",\"schemaTableName\":{\"schema\":\"default\",\"table\":\"5de4aa6bf1138e000101f5fa_green\"},\"partitionColumns\":[{\"@type\":\"hive-hadoop2\",\"name\":\"_athena_commit_id_\",\"hiveType\":\"varchar(32)\",\"typeSignature\":\"varchar(32)\",\"hiveColumnIndex\":-1,\"columnType\":\"PARTITION_KEY\"}],\"compactEffectivePredicate\":{\"columnDomains\":[]},\"promisedPredicate\":{\"columnDomains\":[]}}},\"outputSymbols\":[],\"assignments\":{}},\"aggregations\":{\"count_88\":{\"call\":\"\\\"count\\\"(*)\",\"signature\":{\"name\":\"count\",\"kind\":\"AGGREGATE\",\"typeVariableConstraints\":[],\"longVariableConstraints\":[],\"returnType\":\"bigint\",\"argumentTypes\":[],\"variableArity\":false}}},\"groupingSets\":{\"groupingKeys\":[],\"groupingSetCount\":1,\"globalGroupingSets\":[0]},\"preGroupedSymbols\":[],\"step\":\"PARTIAL\"},\"symbols\":{\"count_88\":\"bigint\"},\"partitioning\":{\"connectorHandle\":{\"@type\":\"$remote\",\"partitioning\":\"SOURCE\",\"function\":\"UNKNOWN\"}},\"partitionedSources\":[\"0\"],\"partitioningScheme\":{\"partitioning\":{\"handle\":{\"connectorHandle\":{\"@type\":\"$remote\",\"partitioning\":\"SINGLE\",\"function\":\"SINGLE\"}},\"arguments\":[]},\"outputLayout\":[\"count_88\"],\"replicateNullsAndAny\":false,\"bucketToPartition\":[0]},\"stageExecutionDescriptor\":{\"strategy\":\"UNGROUPED_EXECUTION\",\"groupedExecutionScanNodes\":[]},\"statsAndCosts\":{\"stats\":{\"174\":{\"outputRowCount\":\"NaN\",\"symbolStatistics\":{}},\"0\":{\"outputRowCount\":\"NaN\",\"symbolStatistics\":{}}},\"costs\":{\"174\":{\"cpuCost\":\"NaN\",\"maxMemory\":\"NaN\",\"maxMemoryWhenOutputting\":\"NaN\",\"networkCost\":\"NaN\",\"rootNodeLocalCostEstimate\":{\"cpuCost\":\"NaN\",\"maxMemory\":\"NaN\",\"networkCost\":\"NaN\"}},\"0\":{\"cpuCost\":0.0,\"maxMemory\":0.0,\"maxMemoryWhenOutputting\":0.0,\"networkCost\":0.0,\"rootNodeLocalCostEstimate\":{\"cpuCost\":0.0,\"maxMemory\":0.0,\"networkCost\":0.0}}}},\"jsonRepresentation\":\"{\\n  \\\"id\\\" : \\\"174\\\",\\n  \\\"name\\\" : \\\"Aggregate(PARTIAL)\\\",\\n  \\\"identifier\\\" : \\\"\\\",\\n  \\\"details\\\" : \\\"count_88 := \\\\\\\"count\\\\\\\"(*)\\\\n\\\",\\n  \\\"children\\\" : [ {\\n    \\\"id\\\" : \\\"0\\\",\\n    \\\"name\\\" : \\\"TableScan\\\",\\n    \\\"identifier\\\" : \\\"[hive:default:5de4aa6bf1138e000101f5fa_green]\\\",\\n    \\\"details\\\" : \\\"_athena_commit_id_:varchar(32):-1:PARTITION_KEY\\\\n    :: [[5de4ac55b4994900cf131116], [5de4af68b499490121d8b292]]\\\\n\\\",\\n    \\\"children\\\" : [ ],\\n    \\\"remoteSources\\\" : [ ]\\n  } ],\\n  \\\"remoteSources\\\" : [ ]\\n}\"},\"types\":[\"bigint\"],\"stageStats\":{\"schedulingComplete\":\"2019-12-10T09:20:58.119Z\",\"getSplitDistribution\":{\"maxError\":0.0,\"count\":11.0,\"total\":1.080184933E9,\"p01\":6361,\"p05\":6361,\"p10\":7259,\"p25\":8410,\"p50\":10556,\"p75\":11388,\"p90\":13690,\"p95\":1080084732,\"p99\":1080084732,\"min\":6361,\"max\":1080084732,\"avg\":9.819863027272727E7},\"totalTasks\":2,\"runningTasks\":0,\"completedTasks\":2,\"totalDrivers\":1097,\"queuedDrivers\":0,\"runningDrivers\":0,\"blockedDrivers\":0,\"completedDrivers\":1097,\"cumulativeUserMemory\":0.0,\"userMemoryReservation\":\"0B\",\"revocableMemoryReservation\":\"0B\",\"totalMemoryReservation\":\"0B\",\"peakUserMemoryReservation\":\"0B\",\"peakRevocableMemoryReservation\":\"0B\",\"totalScheduledTime\":\"2.98m\",\"totalCpuTime\":\"32.49s\",\"totalBlockedTime\":\"0.00ns\",\"fullyBlocked\":false,\"blockedReasons\":[],\"physicalInputDataSize\":\"54.20MB\",\"physicalInputPositions\":3072000000,\"internalNetworkInputDataSize\":\"0B\",\"internalNetworkInputPositions\":0,\"rawInputDataSize\":\"54.20MB\",\"rawInputPositions\":3072000000,\"processedInputDataSize\":\"0B\",\"processedInputPositions\":3072000000,\"bufferedDataSize\":\"0B\",\"outputDataSize\":\"9.64kB\",\"outputPositions\":1097,\"physicalWrittenDataSize\":\"0B\",\"gcInfo\":{\"stageId\":1,\"tasks\":2,\"fullGcTasks\":0,\"minFullGcSec\":0,\"maxFullGcSec\":0,\"totalFullGcSec\":0,\"averageFullGcSec\":0},\"operatorSummaries\":[{\"stageId\":1,\"pipelineId\":0,\"operatorId\":0,\"planNodeId\":\"0\",\"operatorType\":\"TableScanOperator\",\"totalDrivers\":1097,\"addInputCalls\":3081894,\"addInputWall\":\"2.14m\",\"addInputCpu\":\"0.00ns\",\"physicalInputDataSize\":\"54.20MB\",\"physicalInputPositions\":3072000000,\"internalNetworkInputDataSize\":\"0B\",\"internalNetworkInputPositions\":0,\"rawInputDataSize\":\"54.20MB\",\"inputDataSize\":\"0B\",\"inputPositions\":3072000000,\"sumSquaredInputPositions\":1.0295837865770996E16,\"getOutputCalls\":3082991,\"getOutputWall\":\"2.55m\",\"getOutputCpu\":\"17.47s\",\"outputDataSize\":\"0B\",\"outputPositions\":3072000000,\"physicalWrittenDataSize\":\"0B\",\"blockedWall\":\"0.00ns\",\"finishCalls\":0,\"finishWall\":\"0.00ns\",\"finishCpu\":\"0.00ns\",\"userMemoryReservation\":\"0B\",\"revocableMemoryReservation\":\"0B\",\"systemMemoryReservation\":\"0B\",\"peakUserMemoryReservation\":\"0B\",\"peakSystemMemoryReservation\":\"2.35kB\",\"peakRevocableMemoryReservation\":\"0B\",\"peakTotalMemoryReservation\":\"2.35kB\",\"spilledDataSize\":\"0B\"},{\"stageId\":1,\"pipelineId\":0,\"operatorId\":1,\"planNodeId\":\"174\",\"operatorType\":\"AggregationOperator\",\"totalDrivers\":1097,\"addInputCalls\":3081894,\"addInputWall\":\"12.83s\",\"addInputCpu\":\"8.34s\",\"physicalInputDataSize\":\"0B\",\"physicalInputPositions\":0,\"internalNetworkInputDataSize\":\"0B\",\"internalNetworkInputPositions\":0,\"rawInputDataSize\":\"0B\",\"inputDataSize\":\"0B\",\"inputPositions\":3072000000,\"sumSquaredInputPositions\":1.0295837865770996E16,\"getOutputCalls\":3082991,\"getOutputWall\":\"10.58s\",\"getOutputCpu\":\"6.42s\",\"outputDataSize\":\"9.64kB\",\"outputPositions\":1097,\"physicalWrittenDataSize\":\"0B\",\"blockedWall\":\"0.00ns\",\"finishCalls\":1097,\"finishWall\":\"5.20ms\",\"finishCpu\":\"2.88ms\",\"userMemoryReservation\":\"0B\",\"revocableMemoryReservation\":\"0B\",\"systemMemoryReservation\":\"0B\",\"peakUserMemoryReservation\":\"0B\",\"peakSystemMemoryReservation\":\"24B\",\"peakRevocableMemoryReservation\":\"0B\",\"peakTotalMemoryReservation\":\"24B\",\"spilledDataSize\":\"0B\"},{\"stageId\":1,\"pipelineId\":0,\"operatorId\":2,\"planNodeId\":\"174\",\"operatorType\":\"TaskOutputOperator\",\"totalDrivers\":1097,\"addInputCalls\":1097,\"addInputWall\":\"1.62s\",\"addInputCpu\":\"186.17ms\",\"physicalInputDataSize\":\"0B\",\"physicalInputPositions\":0,\"internalNetworkInputDataSize\":\"0B\",\"internalNetworkInputPositions\":0,\"rawInputDataSize\":\"0B\",\"inputDataSize\":\"9.64kB\",\"inputPositions\":1097,\"sumSquaredInputPositions\":1097.0,\"getOutputCalls\":0,\"getOutputWall\":\"0.00ns\",\"getOutputCpu\":\"0.00ns\",\"outputDataSize\":\"9.64kB\",\"outputPositions\":1097,\"physicalWrittenDataSize\":\"0B\",\"blockedWall\":\"0.00ns\",\"finishCalls\":1097,\"finishWall\":\"8.11ms\",\"finishCpu\":\"3.61ms\",\"userMemoryReservation\":\"0B\",\"revocableMemoryReservation\":\"0B\",\"systemMemoryReservation\":\"0B\",\"peakUserMemoryReservation\":\"0B\",\"peakSystemMemoryReservation\":\"0B\",\"peakRevocableMemoryReservation\":\"0B\",\"peakTotalMemoryReservation\":\"0B\",\"spilledDataSize\":\"0B\"}]},\"tasks\":[{\"taskStatus\":{\"taskId\":\"20191210_092032_00000_e5hkw.1.0\",\"taskInstanceId\":\"cf8ae567-05f5-4f13-bfa1-33394a664709\",\"version\":324,\"state\":\"FINISHED\",\"self\":\"http://192.168.43.182:8080/v1/task/20191210_092032_00000_e5hkw.1.0\",\"nodeId\":\"i-0aa03df4d2db9af98\",\"completedDriverGroups\":[],\"failures\":[],\"queuedPartitionedDrivers\":0,\"runningPartitionedDrivers\":0,\"outputBufferOverutilized\":false,\"physicalWrittenDataSize\":\"0B\",\"memoryReservation\":\"0B\",\"systemMemoryReservation\":\"0B\",\"revocableMemoryReservation\":\"0B\",\"fullGcCount\":0,\"fullGcTime\":\"0.00ns\"},\"lastHeartbeat\":\"2019-12-10T09:21:01.731Z\",\"outputBuffers\":{\"type\":\"PARTITIONED\",\"state\":\"FINISHED\",\"canAddBuffers\":false,\"canAddPages\":false,\"totalBufferedBytes\":0,\"totalBufferedPages\":0,\"totalRowsSent\":522,\"totalPagesSent\":522,\"buffers\":[]},\"noMoreSplits\":[\"0\"],\"stats\":{\"createTime\":\"2019-12-10T09:20:37.011Z\",\"firstStartTime\":\"2019-12-10T09:20:37.735Z\",\"lastStartTime\":\"2019-12-10T09:21:01.588Z\",\"lastEndTime\":\"2019-12-10T09:21:01.729Z\",\"endTime\":\"2019-12-10T09:21:01.735Z\",\"elapsedTime\":\"24.17s\",\"queuedTime\":\"168.00ms\",\"totalDrivers\":522,\"queuedDrivers\":0,\"queuedPartitionedDrivers\":0,\"runningDrivers\":0,\"runningPartitionedDrivers\":0,\"blockedDrivers\":0,\"completedDrivers\":522,\"cumulativeUserMemory\":0.0,\"userMemoryReservation\":\"0B\",\"revocableMemoryReservation\":\"0B\",\"systemMemoryReservation\":\"0B\",\"totalScheduledTime\":\"1.55m\",\"totalCpuTime\":\"18.05s\",\"totalBlockedTime\":\"0.00ns\",\"fullyBlocked\":false,\"blockedReasons\":[],\"physicalInputDataSize\":\"22.48MB\",\"physicalInputPositions\":1479858175,\"internalNetworkInputDataSize\":\"0B\",\"internalNetworkInputPositions\":0,\"rawInputDataSize\":\"22.48MB\",\"rawInputPositions\":1479858175,\"processedInputDataSize\":\"0B\",\"processedInputPositions\":1479858175,\"outputDataSize\":\"4.59kB\",\"outputPositions\":522,\"physicalWrittenDataSize\":\"0B\",\"fullGcCount\":0,\"fullGcTime\":\"0.00ns\",\"pipelines\":[{\"pipelineId\":0,\"firstStartTime\":\"2019-12-10T09:20:37.735Z\",\"lastStartTime\":\"2019-12-10T09:21:01.588Z\",\"lastEndTime\":\"2019-12-10T09:21:01.729Z\",\"inputPipeline\":true,\"outputPipeline\":true,\"totalDrivers\":522,\"queuedDrivers\":0,\"queuedPartitionedDrivers\":0,\"runningDrivers\":0,\"runningPartitionedDrivers\":0,\"blockedDrivers\":0,\"completedDrivers\":522,\"userMemoryReservation\":\"0B\",\"revocableMemoryReservation\":\"0B\",\"systemMemoryReservation\":\"0B\",\"queuedTime\":{\"maxError\":0.0,\"count\":522.0,\"total\":1.205649123884E12,\"p01\":2830358,\"p05\":280299379,\"p10\":526312162,\"p25\":1290184450,\"p50\":2299743397,\"p75\":3207602148,\"p90\":3963367382,\"p95\":4456635363,\"p99\":4946699180,\"min\":554386,\"max\":7877390671,\"avg\":2.309672651118774E9},\"elapsedTime\":{\"maxError\":0.0,\"count\":522.0,\"total\":1.298397402304E12,\"p01\":241575130,\"p05\":445036621,\"p10\":753822224,\"p25\":1514500518,\"p50\":2505508021,\"p75\":3381197812,\"p90\":4118005736,\"p95\":4612004843,\"p99\":5060227871,\"min\":103475420,\"max\":7931955269,\"avg\":2.4873513454099617E9},\"totalScheduledTime\":\"1.55m\",\"totalCpuTime\":\"18.05s\",\"totalBlockedTime\":\"0.00ns\",\"fullyBlocked\":false,\"blockedReasons\":[],\"physicalInputDataSize\":\"22.48MB\",\"physicalInputPositions\":1479858175,\"internalNetworkInputDataSize\":\"0B\",\"internalNetworkInputPositions\":0,\"rawInputDataSize\":\"22.48MB\",\"rawInputPositions\":1479858175,\"processedInputDataSize\":\"0B\",\"processedInputPositions\":1479858175,\"outputDataSize\":\"4.59kB\",\"outputPositions\":522,\"physicalWrittenDataSize\":\"0B\",\"operatorSummaries\":[{\"stageId\":1,\"pipelineId\":0,\"operatorId\":0,\"planNodeId\":\"0\",\"operatorType\":\"TableScanOperator\",\"totalDrivers\":522,\"addInputCalls\":1484572,\"addInputWall\":\"1.04m\",\"addInputCpu\":\"0.00ns\",\"physicalInputDataSize\":\"22.48MB\",\"physicalInputPositions\":1479858175,\"internalNetworkInputDataSize\":\"0B\",\"internalNetworkInputPositions\":0,\"rawInputDataSize\":\"22.48MB\",\"inputDataSize\":\"0B\",\"inputPositions\":1479858175,\"sumSquaredInputPositions\":4.997941478348371E15,\"getOutputCalls\":1485094,\"getOutputWall\":\"1.29m\",\"getOutputCpu\":\"9.49s\",\"outputDataSize\":\"0B\",\"outputPositions\":1479858175,\"physicalWrittenDataSize\":\"0B\",\"blockedWall\":\"0.00ns\",\"finishCalls\":0,\"finishWall\":\"0.00ns\",\"finishCpu\":\"0.00ns\",\"userMemoryReservation\":\"0B\",\"revocableMemoryReservation\":\"0B\",\"systemMemoryReservation\":\"0B\",\"peakUserMemoryReservation\":\"0B\",\"peakSystemMemoryReservation\":\"2.33kB\",\"peakRevocableMemoryReservation\":\"0B\",\"peakTotalMemoryReservation\":\"2.33kB\",\"spilledDataSize\":\"0B\"},{\"stageId\":1,\"pipelineId\":0,\"operatorId\":1,\"planNodeId\":\"174\",\"operatorType\":\"AggregationOperator\",\"totalDrivers\":522,\"addInputCalls\":1484572,\"addInputWall\":\"8.45s\",\"addInputCpu\":\"5.27s\",\"physicalInputDataSize\":\"0B\",\"physicalInputPositions\":0,\"internalNetworkInputDataSize\":\"0B\",\"internalNetworkInputPositions\":0,\"rawInputDataSize\":\"0B\",\"inputDataSize\":\"0B\",\"inputPositions\":1479858175,\"sumSquaredInputPositions\":4.997941478348371E15,\"getOutputCalls\":1485094,\"getOutputWall\":\"5.64s\",\"getOutputCpu\":\"3.13s\",\"outputDataSize\":\"4.59kB\",\"outputPositions\":522,\"physicalWrittenDataSize\":\"0B\",\"blockedWall\":\"0.00ns\",\"finishCalls\":522,\"finishWall\":\"3.76ms\",\"finishCpu\":\"1.39ms\",\"userMemoryReservation\":\"0B\",\"revocableMemoryReservation\":\"0B\",\"systemMemoryReservation\":\"0B\",\"peakUserMemoryReservation\":\"0B\",\"peakSystemMemoryReservation\":\"24B\",\"peakRevocableMemoryReservation\":\"0B\",\"peakTotalMemoryReservation\":\"24B\",\"spilledDataSize\":\"0B\"},{\"stageId\":1,\"pipelineId\":0,\"operatorId\":2,\"planNodeId\":\"174\",\"operatorType\":\"TaskOutputOperator\",\"totalDrivers\":522,\"addInputCalls\":522,\"addInputWall\":\"1.05s\",\"addInputCpu\":\"119.60ms\",\"physicalInputDataSize\":\"0B\",\"physicalInputPositions\":0,\"internalNetworkInputDataSize\":\"0B\",\"internalNetworkInputPositions\":0,\"rawInputDataSize\":\"0B\",\"inputDataSize\":\"4.59kB\",\"inputPositions\":522,\"sumSquaredInputPositions\":522.0,\"getOutputCalls\":0,\"getOutputWall\":\"0.00ns\",\"getOutputCpu\":\"0.00ns\",\"outputDataSize\":\"4.59kB\",\"outputPositions\":522,\"physicalWrittenDataSize\":\"0B\",\"blockedWall\":\"0.00ns\",\"finishCalls\":522,\"finishWall\":\"6.16ms\",\"finishCpu\":\"1.64ms\",\"userMemoryReservation\":\"0B\",\"revocableMemoryReservation\":\"0B\",\"systemMemoryReservation\":\"0B\",\"peakUserMemoryReservation\":\"0B\",\"peakSystemMemoryReservation\":\"0B\",\"peakRevocableMemoryReservation\":\"0B\",\"peakTotalMemoryReservation\":\"0B\",\"spilledDataSize\":\"0B\"}],\"drivers\":[]}]},\"needsPlan\":false},{\"taskStatus\":{\"taskId\":\"20191210_092032_00000_e5hkw.1.1\",\"taskInstanceId\":\"4501ea7c-7e0f-4c28-85d3-028e4e953075\",\"version\":328,\"state\":\"FINISHED\",\"self\":\"http://192.168.40.119:8080/v1/task/20191210_092032_00000_e5hkw.1.1\",\"nodeId\":\"i-0edd90e78624ec992\",\"completedDriverGroups\":[],\"failures\":[],\"queuedPartitionedDrivers\":0,\"runningPartitionedDrivers\":0,\"outputBufferOverutilized\":false,\"physicalWrittenDataSize\":\"0B\",\"memoryReservation\":\"0B\",\"systemMemoryReservation\":\"0B\",\"revocableMemoryReservation\":\"0B\",\"fullGcCount\":0,\"fullGcTime\":\"0.00ns\"},\"lastHeartbeat\":\"2019-12-10T09:21:01.834Z\",\"outputBuffers\":{\"type\":\"PARTITIONED\",\"state\":\"FINISHED\",\"canAddBuffers\":false,\"canAddPages\":false,\"totalBufferedBytes\":0,\"totalBufferedPages\":0,\"totalRowsSent\":575,\"totalPagesSent\":575,\"buffers\":[]},\"noMoreSplits\":[\"0\"],\"stats\":{\"createTime\":\"2019-12-10T09:20:37.010Z\",\"firstStartTime\":\"2019-12-10T09:20:37.073Z\",\"lastStartTime\":\"2019-12-10T09:21:01.662Z\",\"lastEndTime\":\"2019-12-10T09:21:01.833Z\",\"endTime\":\"2019-12-10T09:21:01.836Z\",\"elapsedTime\":\"24.77s\",\"queuedTime\":\"5.83ms\",\"totalDrivers\":575,\"queuedDrivers\":0,\"queuedPartitionedDrivers\":0,\"runningDrivers\":0,\"runningPartitionedDrivers\":0,\"blockedDrivers\":0,\"completedDrivers\":575,\"cumulativeUserMemory\":0.0,\"userMemoryReservation\":\"0B\",\"revocableMemoryReservation\":\"0B\",\"systemMemoryReservation\":\"0B\",\"totalScheduledTime\":\"1.43m\",\"totalCpuTime\":\"14.44s\",\"totalBlockedTime\":\"0.00ns\",\"fullyBlocked\":false,\"blockedReasons\":[],\"physicalInputDataSize\":\"31.72MB\",\"physicalInputPositions\":1592141825,\"internalNetworkInputDataSize\":\"0B\",\"internalNetworkInputPositions\":0,\"rawInputDataSize\":\"31.72MB\",\"rawInputPositions\":1592141825,\"processedInputDataSize\":\"0B\",\"processedInputPositions\":1592141825,\"outputDataSize\":\"5.05kB\",\"outputPositions\":575,\"physicalWrittenDataSize\":\"0B\",\"fullGcCount\":0,\"fullGcTime\":\"0.00ns\",\"pipelines\":[{\"pipelineId\":0,\"firstStartTime\":\"2019-12-10T09:20:37.073Z\",\"lastStartTime\":\"2019-12-10T09:21:01.662Z\",\"lastEndTime\":\"2019-12-10T09:21:01.833Z\",\"inputPipeline\":true,\"outputPipeline\":true,\"totalDrivers\":575,\"queuedDrivers\":0,\"queuedPartitionedDrivers\":0,\"runningDrivers\":0,\"runningPartitionedDrivers\":0,\"blockedDrivers\":0,\"completedDrivers\":575,\"userMemoryReservation\":\"0B\",\"revocableMemoryReservation\":\"0B\",\"systemMemoryReservation\":\"0B\",\"queuedTime\":{\"maxError\":0.0,\"count\":575.0,\"total\":1.016399542576E12,\"p01\":1769299,\"p05\":94775407,\"p10\":311662885,\"p25\":802238872,\"p50\":1754014515,\"p75\":2686733871,\"p90\":3192396063,\"p95\":3396272427,\"p99\":3679584149,\"min\":250243,\"max\":3757003004,\"avg\":1.7676513783930435E9},\"elapsedTime\":{\"maxError\":0.0,\"count\":575.0,\"total\":1.102051109763E12,\"p01\":107696417,\"p05\":280463203,\"p10\":426389913,\"p25\":997009920,\"p50\":1935963139,\"p75\":2838330737,\"p90\":3326628323,\"p95\":3538108567,\"p99\":3813604020,\"min\":16952942,\"max\":3912725382,\"avg\":1.9166106256747825E9},\"totalScheduledTime\":\"1.43m\",\"totalCpuTime\":\"14.44s\",\"totalBlockedTime\":\"0.00ns\",\"fullyBlocked\":false,\"blockedReasons\":[],\"physicalInputDataSize\":\"31.72MB\",\"physicalInputPositions\":1592141825,\"internalNetworkInputDataSize\":\"0B\",\"internalNetworkInputPositions\":0,\"rawInputDataSize\":\"31.72MB\",\"rawInputPositions\":1592141825,\"processedInputDataSize\":\"0B\",\"processedInputPositions\":1592141825,\"outputDataSize\":\"5.05kB\",\"outputPositions\":575,\"physicalWrittenDataSize\":\"0B\",\"operatorSummaries\":[{\"stageId\":1,\"pipelineId\":0,\"operatorId\":0,\"planNodeId\":\"0\",\"operatorType\":\"TableScanOperator\",\"totalDrivers\":575,\"addInputCalls\":1597322,\"addInputWall\":\"1.10m\",\"addInputCpu\":\"0.00ns\",\"physicalInputDataSize\":\"31.72MB\",\"physicalInputPositions\":1592141825,\"internalNetworkInputDataSize\":\"0B\",\"internalNetworkInputPositions\":0,\"rawInputDataSize\":\"31.72MB\",\"inputDataSize\":\"0B\",\"inputPositions\":1592141825,\"sumSquaredInputPositions\":5.297896387422625E15,\"getOutputCalls\":1597897,\"getOutputWall\":\"1.26m\",\"getOutputCpu\":\"7.98s\",\"outputDataSize\":\"0B\",\"outputPositions\":1592141825,\"physicalWrittenDataSize\":\"0B\",\"blockedWall\":\"0.00ns\",\"finishCalls\":0,\"finishWall\":\"0.00ns\",\"finishCpu\":\"0.00ns\",\"userMemoryReservation\":\"0B\",\"revocableMemoryReservation\":\"0B\",\"systemMemoryReservation\":\"0B\",\"peakUserMemoryReservation\":\"0B\",\"peakSystemMemoryReservation\":\"2.35kB\",\"peakRevocableMemoryReservation\":\"0B\",\"peakTotalMemoryReservation\":\"2.35kB\",\"spilledDataSize\":\"0B\"},{\"stageId\":1,\"pipelineId\":0,\"operatorId\":1,\"planNodeId\":\"174\",\"operatorType\":\"AggregationOperator\",\"totalDrivers\":575,\"addInputCalls\":1597322,\"addInputWall\":\"4.38s\",\"addInputCpu\":\"3.07s\",\"physicalInputDataSize\":\"0B\",\"physicalInputPositions\":0,\"internalNetworkInputDataSize\":\"0B\",\"internalNetworkInputPositions\":0,\"rawInputDataSize\":\"0B\",\"inputDataSize\":\"0B\",\"inputPositions\":1592141825,\"sumSquaredInputPositions\":5.297896387422625E15,\"getOutputCalls\":1597897,\"getOutputWall\":\"4.94s\",\"getOutputCpu\":\"3.29s\",\"outputDataSize\":\"5.05kB\",\"outputPositions\":575,\"physicalWrittenDataSize\":\"0B\",\"blockedWall\":\"0.00ns\",\"finishCalls\":575,\"finishWall\":\"1.44ms\",\"finishCpu\":\"1.49ms\",\"userMemoryReservation\":\"0B\",\"revocableMemoryReservation\":\"0B\",\"systemMemoryReservation\":\"0B\",\"peakUserMemoryReservation\":\"0B\",\"peakSystemMemoryReservation\":\"24B\",\"peakRevocableMemoryReservation\":\"0B\",\"peakTotalMemoryReservation\":\"24B\",\"spilledDataSize\":\"0B\"},{\"stageId\":1,\"pipelineId\":0,\"operatorId\":2,\"planNodeId\":\"174\",\"operatorType\":\"TaskOutputOperator\",\"totalDrivers\":575,\"addInputCalls\":575,\"addInputWall\":\"570.97ms\",\"addInputCpu\":\"66.57ms\",\"physicalInputDataSize\":\"0B\",\"physicalInputPositions\":0,\"internalNetworkInputDataSize\":\"0B\",\"internalNetworkInputPositions\":0,\"rawInputDataSize\":\"0B\",\"inputDataSize\":\"5.05kB\",\"inputPositions\":575,\"sumSquaredInputPositions\":575.0,\"getOutputCalls\":0,\"getOutputWall\":\"0.00ns\",\"getOutputCpu\":\"0.00ns\",\"outputDataSize\":\"5.05kB\",\"outputPositions\":575,\"physicalWrittenDataSize\":\"0B\",\"blockedWall\":\"0.00ns\",\"finishCalls\":575,\"finishWall\":\"1.95ms\",\"finishCpu\":\"1.97ms\",\"userMemoryReservation\":\"0B\",\"revocableMemoryReservation\":\"0B\",\"systemMemoryReservation\":\"0B\",\"peakUserMemoryReservation\":\"0B\",\"peakSystemMemoryReservation\":\"0B\",\"peakRevocableMemoryReservation\":\"0B\",\"peakTotalMemoryReservation\":\"0B\",\"spilledDataSize\":\"0B\"}],\"drivers\":[]}]},\"needsPlan\":false}],\"subStages\":[]}]}",
        "spilledDataSize": 0,
        "queryTransactionId": "45191293-d259-4acb-a881-c1eee0257919",
        "internalNetworkRows": 1097,
        "completedSplits": 1114,
        "waitingTime": 1,
        "peakTotalNonRevocableMemoryBytes": 12101,
        "peakTaskTotalMemory": 9456,
        "physicalInputBytes": 56832818,
        "physicalWrittenData": 0,
        "planNodeStatsAndCosts": "{\"stats\":{\"14\":{\"outputRowCount\":\"NaN\",\"symbolStatistics\":{}},\"9\":{\"outputRowCount\":\"NaN\",\"symbolStatistics\":{}},\"170\":{\"outputRowCount\":\"NaN\",\"symbolStatistics\":{}},\"176\":{\"outputRowCount\":\"NaN\",\"symbolStatistics\":{}},\"174\":{\"outputRowCount\":\"NaN\",\"symbolStatistics\":{}},\"0\":{\"outputRowCount\":\"NaN\",\"symbolStatistics\":{}}},\"costs\":{\"14\":{\"cpuCost\":\"NaN\",\"maxMemory\":\"NaN\",\"maxMemoryWhenOutputting\":\"NaN\",\"networkCost\":\"NaN\",\"rootNodeLocalCostEstimate\":{\"cpuCost\":0.0,\"maxMemory\":0.0,\"networkCost\":0.0}},\"9\":{\"cpuCost\":\"NaN\",\"maxMemory\":\"NaN\",\"maxMemoryWhenOutputting\":\"NaN\",\"networkCost\":\"NaN\",\"rootNodeLocalCostEstimate\":{\"cpuCost\":\"NaN\",\"maxMemory\":\"NaN\",\"networkCost\":0.0}},\"170\":{\"cpuCost\":\"NaN\",\"maxMemory\":\"NaN\",\"maxMemoryWhenOutputting\":\"NaN\",\"networkCost\":\"NaN\",\"rootNodeLocalCostEstimate\":{\"cpuCost\":0.0,\"maxMemory\":0.0,\"networkCost\":0.0}},\"176\":{\"cpuCost\":\"NaN\",\"maxMemory\":\"NaN\",\"maxMemoryWhenOutputting\":\"NaN\",\"networkCost\":\"NaN\",\"rootNodeLocalCostEstimate\":{\"cpuCost\":0.0,\"maxMemory\":0.0,\"networkCost\":\"NaN\"}},\"174\":{\"cpuCost\":\"NaN\",\"maxMemory\":\"NaN\",\"maxMemoryWhenOutputting\":\"NaN\",\"networkCost\":\"NaN\",\"rootNodeLocalCostEstimate\":{\"cpuCost\":\"NaN\",\"maxMemory\":\"NaN\",\"networkCost\":\"NaN\"}},\"0\":{\"cpuCost\":0.0,\"maxMemory\":0.0,\"maxMemoryWhenOutputting\":0.0,\"networkCost\":0.0,\"rootNodeLocalCostEstimate\":{\"cpuCost\":0.0,\"maxMemory\":0.0,\"networkCost\":0.0}}}}",
        "prestoWarnings": "",
        "cpuTime": 32,
        "peakTaskUserMemory": 24,
        "totalBytes": 56832818,
        "queryPlan": "Fragment 0 [SINGLE]\n    CPU: 136.86ms, Scheduled: 287.61ms, Input: 1097 rows (9.64kB); per task: avg.: 1097.00 std.dev.: 0.00, Output: 1 row (9B)\n    Output layout: [count]\n    Output partitioning: SINGLE []\n    Stage Execution Strategy: UNGROUPED_EXECUTION\n    - Output[_col0]\n            Layout: [count:bigint]\n            Estimates: {rows: ? (?), cpu: ?, memory: ?, network: ?}\n            CPU: 0.00ns (0.00%), Scheduled: 0.00ns (0.00%), Output: 1 row (9B)\n            Input avg.: 1.00 rows, Input std.dev.: 0.00%\n            _col0 := count\n        - Aggregate(FINAL)\n                Layout: [count:bigint]\n                Estimates: {rows: ? (?), cpu: ?, memory: ?, network: ?}\n                CPU: 14.00ms (0.00%), Scheduled: 18.00ms (0.06%), Output: 1 row (9B)\n                Input avg.: 1097.00 rows, Input std.dev.: 0.00%\n                count := \"count\"(\"count_88\")\n            - LocalExchange[SINGLE] ()\n                    Layout: [count_88:bigint]\n                    Estimates: {rows: ? (?), cpu: ?, memory: ?, network: ?}\n                    CPU: 32.00ms (0.01%), Scheduled: 99.00ms (0.30%), Output: 1097 rows (9.64kB)\n                    Input avg.: 68.56 rows, Input std.dev.: 310.46%\n                - RemoteSource[1]\n                        Layout: [count_88:bigint]\n                        CPU: 35.00ms (0.01%), Scheduled: 82.00ms (0.25%), Output: 1097 rows (9.64kB)\n                        Input avg.: 68.56 rows, Input std.dev.: 310.46%\n\nFragment 1 [SOURCE]\n    CPU: 32.49s, Scheduled: 2.98m, Input: 3072000000 rows (0B); per task: avg.: 1536000000.00 std.dev.: 56141825.00, Output: 1097 rows (9.64kB)\n    Output layout: [count_88]\n    Output partitioning: SINGLE []\n    Stage Execution Strategy: UNGROUPED_EXECUTION\n    - Aggregate(PARTIAL)\n            Layout: [count_88:bigint]\n            CPU: 14.95s (4.88%), Scheduled: 25.04s (77.05%), Output: 1097 rows (9.64kB)\n            Input avg.: 2800364.63 rows, Input std.dev.: 44.36%\n            count_88 := \"count\"(*)\n        - TableScan[hive:default:5de4aa6bf1138e000101f5fa_green, grouped = false]\n                Layout: []\n                Estimates: {rows: ? (0B), cpu: 0, memory: 0B, network: 0B}\n                CPU: 17.47s (5.70%), Scheduled: 4.69m (865.74%), Output: 3072000000 rows (0B)\n                Input avg.: 2800364.63 rows, Input std.dev.: 44.36%\n\n",
        "peakUserMemoryBytes": 24,
        "sessionProperties": "spill_enabled=true",
        "queuedTime": 0,
        "totalRows": 3072000000,
        "outputRows": 1,
        "outputBytes": 9,
        "writtenBytes": 0,
        "writtenRows": 0,
        "cumulativeMemory": 583059,
        "distributedPlanningTime": 0,
        "internalNetworkBytes": 34007,
        "createTime": "2019-12-10T09:20:32.889Z",
        "wallTime": 179,
        "executionStartTime": "2019-12-10T09:20:34.713Z",
        "endTime": "2019-12-10T09:21:01.889Z",
        "operatorSummaries": [
            "{\"stageId\":0,\"pipelineId\":0,\"operatorId\":0,\"planNodeId\":\"176\",\"operatorType\":\"ExchangeOperator\",\"totalDrivers\":16,\"addInputCalls\":0,\"addInputWall\":\"0.00ns\",\"addInputCpu\":\"0.00ns\",\"physicalInputDataSize\":\"0B\",\"physicalInputPositions\":0,\"internalNetworkInputDataSize\":\"33.21kB\",\"internalNetworkInputPositions\":1097,\"rawInputDataSize\":\"33.21kB\",\"inputDataSize\":\"9.64kB\",\"inputPositions\":1097,\"sumSquaredInputPositions\":800179.0,\"getOutputCalls\":1110,\"getOutputWall\":\"82.09ms\",\"getOutputCpu\":\"34.66ms\",\"outputDataSize\":\"9.64kB\",\"outputPositions\":1097,\"physicalWrittenDataSize\":\"0B\",\"blockedWall\":\"3.15m\",\"finishCalls\":0,\"finishWall\":\"0.00ns\",\"finishCpu\":\"0.00ns\",\"userMemoryReservation\":\"0B\",\"revocableMemoryReservation\":\"0B\",\"systemMemoryReservation\":\"0B\",\"peakUserMemoryReservation\":\"0B\",\"peakSystemMemoryReservation\":\"0B\",\"peakRevocableMemoryReservation\":\"0B\",\"peakTotalMemoryReservation\":\"0B\",\"spilledDataSize\":\"0B\",\"info\":{\"@type\":\"exchangeClientStatus\",\"bufferedBytes\":0,\"maxBufferedBytes\":889,\"averageBytesPerRequest\":0,\"successfulRequestsCount\":17520,\"bufferedPages\":0,\"noMoreLocations\":true,\"pageBufferClientStatuses\":[]}}",
            "{\"stageId\":0,\"pipelineId\":1,\"operatorId\":0,\"planNodeId\":\"170\",\"operatorType\":\"LocalExchangeSourceOperator\",\"totalDrivers\":1,\"addInputCalls\":0,\"addInputWall\":\"0.00ns\",\"addInputCpu\":\"0.00ns\",\"physicalInputDataSize\":\"0B\",\"physicalInputPositions\":0,\"internalNetworkInputDataSize\":\"0B\",\"internalNetworkInputPositions\":0,\"rawInputDataSize\":\"0B\",\"inputDataSize\":\"9.64kB\",\"inputPositions\":1097,\"sumSquaredInputPositions\":1203409.0,\"getOutputCalls\":1097,\"getOutputWall\":\"12.31ms\",\"getOutputCpu\":\"9.61ms\",\"outputDataSize\":\"9.64kB\",\"outputPositions\":1097,\"physicalWrittenDataSize\":\"0B\",\"blockedWall\":\"22.14s\",\"finishCalls\":0,\"finishWall\":\"0.00ns\",\"finishCpu\":\"0.00ns\",\"userMemoryReservation\":\"0B\",\"revocableMemoryReservation\":\"0B\",\"systemMemoryReservation\":\"0B\",\"peakUserMemoryReservation\":\"0B\",\"peakSystemMemoryReservation\":\"0B\",\"peakRevocableMemoryReservation\":\"0B\",\"peakTotalMemoryReservation\":\"0B\",\"spilledDataSize\":\"0B\"}",
            "{\"stageId\":0,\"pipelineId\":0,\"operatorId\":1,\"planNodeId\":\"170\",\"operatorType\":\"LocalExchangeSinkOperator\",\"totalDrivers\":16,\"addInputCalls\":1097,\"addInputWall\":\"85.19ms\",\"addInputCpu\":\"21.16ms\",\"physicalInputDataSize\":\"0B\",\"physicalInputPositions\":0,\"internalNetworkInputDataSize\":\"0B\",\"internalNetworkInputPositions\":0,\"rawInputDataSize\":\"0B\",\"inputDataSize\":\"9.64kB\",\"inputPositions\":1097,\"sumSquaredInputPositions\":800179.0,\"getOutputCalls\":0,\"getOutputWall\":\"0.00ns\",\"getOutputCpu\":\"0.00ns\",\"outputDataSize\":\"9.64kB\",\"outputPositions\":1097,\"physicalWrittenDataSize\":\"0B\",\"blockedWall\":\"0.00ns\",\"finishCalls\":16,\"finishWall\":\"2.29ms\",\"finishCpu\":\"806.26us\",\"userMemoryReservation\":\"0B\",\"revocableMemoryReservation\":\"0B\",\"systemMemoryReservation\":\"0B\",\"peakUserMemoryReservation\":\"0B\",\"peakSystemMemoryReservation\":\"0B\",\"peakRevocableMemoryReservation\":\"0B\",\"peakTotalMemoryReservation\":\"0B\",\"spilledDataSize\":\"0B\"}",
            "{\"stageId\":0,\"pipelineId\":1,\"operatorId\":1,\"planNodeId\":\"9\",\"operatorType\":\"AggregationOperator\",\"totalDrivers\":1,\"addInputCalls\":1097,\"addInputWall\":\"10.09ms\",\"addInputCpu\":\"8.64ms\",\"physicalInputDataSize\":\"0B\",\"physicalInputPositions\":0,\"internalNetworkInputDataSize\":\"0B\",\"internalNetworkInputPositions\":0,\"rawInputDataSize\":\"0B\",\"inputDataSize\":\"9.64kB\",\"inputPositions\":1097,\"sumSquaredInputPositions\":1203409.0,\"getOutputCalls\":1580,\"getOutputWall\":\"7.67ms\",\"getOutputCpu\":\"4.75ms\",\"outputDataSize\":\"9B\",\"outputPositions\":1,\"physicalWrittenDataSize\":\"0B\",\"blockedWall\":\"0.00ns\",\"finishCalls\":1,\"finishWall\":\"23.81us\",\"finishCpu\":\"22.44us\",\"userMemoryReservation\":\"0B\",\"revocableMemoryReservation\":\"0B\",\"systemMemoryReservation\":\"0B\",\"peakUserMemoryReservation\":\"24B\",\"peakSystemMemoryReservation\":\"0B\",\"peakRevocableMemoryReservation\":\"0B\",\"peakTotalMemoryReservation\":\"24B\",\"spilledDataSize\":\"0B\"}",
            "{\"stageId\":0,\"pipelineId\":1,\"operatorId\":2,\"planNodeId\":\"14\",\"operatorType\":\"TaskOutputOperator\",\"totalDrivers\":1,\"addInputCalls\":1,\"addInputWall\":\"98.74us\",\"addInputCpu\":\"99.31us\",\"physicalInputDataSize\":\"0B\",\"physicalInputPositions\":0,\"internalNetworkInputDataSize\":\"0B\",\"internalNetworkInputPositions\":0,\"rawInputDataSize\":\"0B\",\"inputDataSize\":\"9B\",\"inputPositions\":1,\"sumSquaredInputPositions\":1.0,\"getOutputCalls\":0,\"getOutputWall\":\"0.00ns\",\"getOutputCpu\":\"0.00ns\",\"outputDataSize\":\"9B\",\"outputPositions\":1,\"physicalWrittenDataSize\":\"0B\",\"blockedWall\":\"0.00ns\",\"finishCalls\":1,\"finishWall\":\"3.31us\",\"finishCpu\":\"3.34us\",\"userMemoryReservation\":\"0B\",\"revocableMemoryReservation\":\"0B\",\"systemMemoryReservation\":\"0B\",\"peakUserMemoryReservation\":\"0B\",\"peakSystemMemoryReservation\":\"0B\",\"peakRevocableMemoryReservation\":\"0B\",\"peakTotalMemoryReservation\":\"0B\",\"spilledDataSize\":\"0B\"}",
            "{\"stageId\":1,\"pipelineId\":0,\"operatorId\":0,\"planNodeId\":\"0\",\"operatorType\":\"TableScanOperator\",\"totalDrivers\":1097,\"addInputCalls\":3081894,\"addInputWall\":\"2.14m\",\"addInputCpu\":\"0.00ns\",\"physicalInputDataSize\":\"54.20MB\",\"physicalInputPositions\":3072000000,\"internalNetworkInputDataSize\":\"0B\",\"internalNetworkInputPositions\":0,\"rawInputDataSize\":\"54.20MB\",\"inputDataSize\":\"0B\",\"inputPositions\":3072000000,\"sumSquaredInputPositions\":1.0295837865770996E16,\"getOutputCalls\":3082991,\"getOutputWall\":\"2.55m\",\"getOutputCpu\":\"17.47s\",\"outputDataSize\":\"0B\",\"outputPositions\":3072000000,\"physicalWrittenDataSize\":\"0B\",\"blockedWall\":\"0.00ns\",\"finishCalls\":0,\"finishWall\":\"0.00ns\",\"finishCpu\":\"0.00ns\",\"userMemoryReservation\":\"0B\",\"revocableMemoryReservation\":\"0B\",\"systemMemoryReservation\":\"0B\",\"peakUserMemoryReservation\":\"0B\",\"peakSystemMemoryReservation\":\"2.35kB\",\"peakRevocableMemoryReservation\":\"0B\",\"peakTotalMemoryReservation\":\"2.35kB\",\"spilledDataSize\":\"0B\"}",
            "{\"stageId\":1,\"pipelineId\":0,\"operatorId\":1,\"planNodeId\":\"174\",\"operatorType\":\"AggregationOperator\",\"totalDrivers\":1097,\"addInputCalls\":3081894,\"addInputWall\":\"12.83s\",\"addInputCpu\":\"8.34s\",\"physicalInputDataSize\":\"0B\",\"physicalInputPositions\":0,\"internalNetworkInputDataSize\":\"0B\",\"internalNetworkInputPositions\":0,\"rawInputDataSize\":\"0B\",\"inputDataSize\":\"0B\",\"inputPositions\":3072000000,\"sumSquaredInputPositions\":1.0295837865770996E16,\"getOutputCalls\":3082991,\"getOutputWall\":\"10.58s\",\"getOutputCpu\":\"6.42s\",\"outputDataSize\":\"9.64kB\",\"outputPositions\":1097,\"physicalWrittenDataSize\":\"0B\",\"blockedWall\":\"0.00ns\",\"finishCalls\":1097,\"finishWall\":\"5.20ms\",\"finishCpu\":\"2.88ms\",\"userMemoryReservation\":\"0B\",\"revocableMemoryReservation\":\"0B\",\"systemMemoryReservation\":\"0B\",\"peakUserMemoryReservation\":\"0B\",\"peakSystemMemoryReservation\":\"24B\",\"peakRevocableMemoryReservation\":\"0B\",\"peakTotalMemoryReservation\":\"24B\",\"spilledDataSize\":\"0B\"}",
            "{\"stageId\":1,\"pipelineId\":0,\"operatorId\":2,\"planNodeId\":\"174\",\"operatorType\":\"TaskOutputOperator\",\"totalDrivers\":1097,\"addInputCalls\":1097,\"addInputWall\":\"1.62s\",\"addInputCpu\":\"186.17ms\",\"physicalInputDataSize\":\"0B\",\"physicalInputPositions\":0,\"internalNetworkInputDataSize\":\"0B\",\"internalNetworkInputPositions\":0,\"rawInputDataSize\":\"0B\",\"inputDataSize\":\"9.64kB\",\"inputPositions\":1097,\"sumSquaredInputPositions\":1097.0,\"getOutputCalls\":0,\"getOutputWall\":\"0.00ns\",\"getOutputCpu\":\"0.00ns\",\"outputDataSize\":\"9.64kB\",\"outputPositions\":1097,\"physicalWrittenDataSize\":\"0B\",\"blockedWall\":\"0.00ns\",\"finishCalls\":1097,\"finishWall\":\"8.11ms\",\"finishCpu\":\"3.61ms\",\"userMemoryReservation\":\"0B\",\"revocableMemoryReservation\":\"0B\",\"systemMemoryReservation\":\"0B\",\"peakUserMemoryReservation\":\"0B\",\"peakSystemMemoryReservation\":\"0B\",\"peakRevocableMemoryReservation\":\"0B\",\"peakTotalMemoryReservation\":\"0B\",\"spilledDataSize\":\"0B\"}"
        ]
    },
    "fields": {
        "createdAt": [
            "2019-12-10T09:20:32.889Z"
        ],
        "createTime": [
            "2019-12-10T09:20:32.889Z"
        ],
        "executionStartTime": [
            "2019-12-10T09:20:34.713Z"
        ],
        "endTime": [
            "2019-12-10T09:21:01.889Z"
        ]
    },
    "sort": [
        1575969632889
    ]
}